README.md
setup.py
afeSMS/__init__.py
afeSMS.egg-info/PKG-INFO
afeSMS.egg-info/SOURCES.txt
afeSMS.egg-info/dependency_links.txt
afeSMS.egg-info/requires.txt
afeSMS.egg-info/top_level.txt