Metadata-Version: 2.1
Name: afeSMS
Version: 1.0.0
Summary: afe SMS sender Python package
Author: Morteza Sotoodeh
Author-email: sotoodeh@afe.ir
